craps/__init__.py
craps/models.py
craps/utils.py
craps/algos/__init__.py
craps/algos/threepointmolly.py
src/__init__.py
src/models.py
src/utils.py
src/algos/__init__.py
src/algos/threepointmolly.py
craps-2.0.2.dist-info/LICENCE
craps-2.0.2.dist-info/METADATA
craps-2.0.2.dist-info/WHEEL
craps-2.0.2.dist-info/top_level.txt
craps-2.0.2.dist-info/RECORD
