Metadata-Version: 2.1
Name: craps
Version: 2.0.2
Summary: A table game engine.
Home-page: https://github.com/mhegarty/craps
Author: Mike Hegarty
Author-email: mike@petorca.com
License: MIT
Platform: UNKNOWN
Classifier: License :: OSI Approved :: MIT License
Classifier: Programming Language :: Python :: 3
Classifier: Programming Language :: Python :: 3.8
License-File: LICENCE
Requires-Dist: appdirs
